openai_image/__init__.py
openai_image/main.py
openai_image-1.0.5.dist-info/LICENSE
openai_image-1.0.5.dist-info/METADATA
openai_image-1.0.5.dist-info/WHEEL
openai_image-1.0.5.dist-info/top_level.txt
openai_image-1.0.5.dist-info/RECORD
