Metadata-Version: 2.1
Name: openai-image
Version: 1.0.5
Summary: Python script for generating image from text by Open AI
Home-page: https://github.com/IgorMan2005/openai_image/
Author: IgorMan
Author-email: igorman2005@gmail.com
Project-URL: Documentation, https://best-itpro.ru/news/openai_image/
Keywords: openai image api open ai python
Classifier: Programming Language :: Python :: 3.11
Classifier: License :: OSI Approved :: MIT License
Classifier: Operating System :: OS Independent
Requires-Python: >=3.6
License-File: LICENSE
Requires-Dist: openai
